py_smsify/__init__.py
py_smsify-0.2.1.dist-info/LICENSE
py_smsify-0.2.1.dist-info/WHEEL
py_smsify-0.2.1.dist-info/METADATA
py_smsify-0.2.1.dist-info/RECORD
