Metadata-Version: 2.1
Name: py-smsify
Version: 0.2.1
Summary: Python library for creating GSM-7 compatible SMS messages
Home-page: https://github.com/SkyDiverCool/py-smsify
License: MIT
Keywords: SMS,GSM-7,Encoding,Unicode,3GPP,23.038,03.38
Author: Simon Wissotsky
Author-email: Wissotsky@protonmail.com
Requires-Python: >=3.9,<4.0
Classifier: Development Status :: 4 - Beta
Classifier: Intended Audience :: Developers
Classifier: Intended Audience :: Telecommunications Industry
Classifier: License :: OSI Approved :: MIT License
Classifier: Programming Language :: Python :: 3
Classifier: Programming Language :: Python :: 3.10
Classifier: Programming Language :: Python :: 3.9
Classifier: Topic :: Communications :: Telephony
Classifier: Topic :: Text Processing :: Filters
Requires-Dist: anyascii (>=0.3.1,<0.4.0)
Project-URL: Repository, https://github.com/SkyDiverCool/py-smsify
